persession/__init__.py
persession/main.py
persession/persession.py
persession/test.py
persession-0.1.4.dist-info/LICENSE
persession-0.1.4.dist-info/METADATA
persession-0.1.4.dist-info/WHEEL
persession-0.1.4.dist-info/top_level.txt
persession-0.1.4.dist-info/RECORD
