Metadata-Version: 2.1
Name: persession
Version: 0.1.4
Summary: A wrapper on requests session with persistence and login functionalities
Home-page: https://github.com/rishabhsingh971/persession
Author: Rishabh Singh
Author-email: rishabhsingh971@gmail.com
License: MIT
Project-URL: Documentation, https://github.com/rishabhsingh971/persession/README.md
Project-URL: Source, https://github.com/rishabhsingh971/persession/
Project-URL: Tracker, https://github.com/rishabhsingh971/persession/issues
Keywords: requests session persistent login utility development
Platform: UNKNOWN
Classifier: License :: OSI Approved :: MIT License
Classifier: Development Status :: 3 - Alpha
Classifier: Programming Language :: Python :: 3
Classifier: Operating System :: OS Independent
Classifier: Intended Audience :: Developers
Requires-Python: >=3
Requires-Dist: requests
